t2s/__init__.py
t2s/cli.py
t2s/core/__init__.py
t2s/core/config.py
t2s/core/engine.py
t2s/core/mql_engine.py
t2s/core/sql_engine.py
t2s/database/__init__.py
t2s/database/db_manager.py
t2s/database/mongodb_manager.py
t2s/models/__init__.py
t2s/models/external_api_manager.py
t2s/models/model_manager.py
t2s/ui/__init__.py
t2s/ui/ascii_art.py
t2s/utils/__init__.py
t2s/utils/mql_validator.py
t2s/utils/schema_analyzer.py
t2s/utils/sql_validator.py
t2s_cli-0.3.2.dist-info/licenses/LICENSE
t2s_cli-0.3.2.dist-info/METADATA
t2s_cli-0.3.2.dist-info/WHEEL
t2s_cli-0.3.2.dist-info/entry_points.txt
t2s_cli-0.3.2.dist-info/top_level.txt
t2s_cli-0.3.2.dist-info/RECORD
