Metadata-Version: 2.4
Name: t2s-cli
Version: 0.3.2
Summary: Terminal-based Text-to-SQL and Text-to-MQL converter with local and cloud AI model integration
Author: Lakshman Turlapati
Author-email: lakshmanturlapati@gmail.com
License: MIT
Project-URL: Homepage, https://github.com/lakshmanturlapati/t2s-cli
Project-URL: Repository, https://github.com/lakshmanturlapati/t2s-cli
Project-URL: Documentation, https://github.com/lakshmanturlapati/t2s-cli#readme
Project-URL: Issues, https://github.com/lakshmanturlapati/t2s-cli/issues
Keywords: sql,mongodb,text-to-sql,text-to-mql,ai,database,cli,terminal,nosql
Classifier: Development Status :: 4 - Beta
Classifier: Intended Audience :: Developers
Classifier: License :: OSI Approved :: MIT License
Classifier: Operating System :: OS Independent
Classifier: Programming Language :: Python :: 3
Classifier: Programming Language :: Python :: 3.9
Classifier: Programming Language :: Python :: 3.10
Classifier: Programming Language :: Python :: 3.11
Classifier: Programming Language :: Python :: 3.12
Classifier: Topic :: Database
Classifier: Topic :: Software Development :: Libraries :: Python Modules
Requires-Python: >=3.9
License-File: LICENSE
Requires-Dist: torch>=2.0.0
Requires-Dist: transformers>=4.40.0
Requires-Dist: accelerate>=0.25.0
Requires-Dist: huggingface-hub>=0.20.0
Requires-Dist: datasets>=2.16.0
Requires-Dist: tokenizers>=0.15.0
Requires-Dist: sentencepiece>=0.1.99
Requires-Dist: protobuf>=3.20.0
Requires-Dist: rich>=13.0.0
Requires-Dist: click>=8.1.0
Requires-Dist: questionary>=2.0.0
Requires-Dist: art>=6.0
Requires-Dist: tabulate>=0.9.0
Requires-Dist: pandas>=2.0.0
Requires-Dist: sqlalchemy>=2.0.0
Requires-Dist: sqlparse>=0.4.0
Requires-Dist: psycopg2-binary>=2.9.0
Requires-Dist: pymysql>=1.0.0
Requires-Dist: pymongo>=4.6.0
Requires-Dist: python-dotenv>=1.0.0
Requires-Dist: pydantic>=2.0.0
Requires-Dist: pillow>=9.0.0
Requires-Dist: anthropic>=0.40.0
Requires-Dist: openai>=1.0.0
Requires-Dist: google-genai>=0.8.0
Provides-Extra: gemma
Requires-Dist: sentencepiece>=0.1.99; extra == "gemma"
Provides-Extra: test
Requires-Dist: pytest>=7.0.0; extra == "test"
Requires-Dist: pytest-cov>=4.0.0; extra == "test"
Requires-Dist: pytest-mock>=3.10.0; extra == "test"
Requires-Dist: pytest-asyncio>=0.21.0; extra == "test"
Provides-Extra: dev
Requires-Dist: pytest>=7.0.0; extra == "dev"
Requires-Dist: pytest-cov>=4.0.0; extra == "dev"
Requires-Dist: pytest-mock>=3.10.0; extra == "dev"
Requires-Dist: pytest-asyncio>=0.21.0; extra == "dev"
Requires-Dist: black>=23.0.0; extra == "dev"
Requires-Dist: isort>=5.12.0; extra == "dev"
Requires-Dist: flake8>=6.0.0; extra == "dev"
Requires-Dist: mypy>=1.4.0; extra == "dev"
Requires-Dist: pre-commit>=3.0.0; extra == "dev"
Requires-Dist: build>=0.10.0; extra == "dev"
Requires-Dist: twine>=4.0.0; extra == "dev"
Provides-Extra: all
Requires-Dist: sentencepiece>=0.1.99; extra == "all"
Requires-Dist: pytest>=7.0.0; extra == "all"
Requires-Dist: pytest-cov>=4.0.0; extra == "all"
Requires-Dist: pytest-mock>=3.10.0; extra == "all"
Requires-Dist: pytest-asyncio>=0.21.0; extra == "all"
Dynamic: license-file
